nuse/__init__.py
nuse/monitor2.py
nuse/nuse.py
nuse-0.1.8.dist-info/METADATA
nuse-0.1.8.dist-info/WHEEL
nuse-0.1.8.dist-info/entry_points.txt
nuse-0.1.8.dist-info/top_level.txt
nuse-0.1.8.dist-info/RECORD
