Metadata-Version: 2.1
Name: nuse
Version: 0.1.8
Summary: A simple resource monitoring tool for SLURM jobs.
Home-page: https://github.com/MolinDiscovery/nuse
Author: Jacob Molin Nielsen
Author-email: jacob.molin@me.com
